Metadata-Version: 2.1
Name: sc4net
Version: 0.1.3
Summary: Shortcuts for user with requests and requests_ftp
Home-page: https://github.com/kelsoncm/sc4
Author: Kelson da Costa Medeiros
Author-email: kelsoncm@gmail.com
License: UNKNOWN
Download-URL: https://github.com/kelsoncm/pyatalhos/releases/tag/sc4net-v0.1.3
Keywords: shortcuts,requests,requests_ftp
Platform: UNKNOWN
License-File: LICENSE.txt
